[
  {
    "link": "https://pikabu.ru/community/true_story",
    "title": "Истории из жизни",
    "rating": 424797
  },
  {
    "link": "https://pikabu.ru/community/comics",
    "title": "Комиксы",
    "rating": 364720
  },
  {
    "link": "https://pikabu.ru/community/skrincom",
    "title": "Скриншоты коментов",
    "rating": 324345
  },
  {
    "link": "https://pikabu.ru/community/Throne_League",
    "title": "Лига Престолов",
    "rating": 297954
  },
  {
    "link": "https://pikabu.ru/community/novosti",
    "title": "Новости",
    "rating": 161034
  },
  {
    "link": "https://pikabu.ru/community/kotiki_obormotiki",
    "title": "Котомафия",
    "rating": 159276
  },
  {
    "link": "https://pikabu.ru/community/aww",
    "title": "Милота",
    "rating": 96363
  },
  {
    "link": "https://pikabu.ru/community/cynicmansion",
    "title": "Cynic Mansion",
    "rating": 79229
  },
  {
    "link": "https://pikabu.ru/community/gamers",
    "title": "Лига Геймеров",
    "rating": 74061
  },
  {
    "link": "https://pikabu.ru/community/auto",
    "title": "Автомобильное сообщество",
    "rating": 70474
  },
  {
    "link": "https://pikabu.ru/community/justice",
    "title": "Лига Юристов",
    "rating": 63478
  },
  {
    "link": "https://pikabu.ru/community/photographers",
    "title": "Лига фотографов",
    "rating": 54393
  },
  {
    "link": "https://pikabu.ru/community/dogs_weekdays",
    "title": "Собачьи будни",
    "rating": 48257
  },
  {
    "link": "https://pikabu.ru/community/hand_made",
    "title": "Рукодельники",
    "rating": 47715
  },
  {
    "link": "https://pikabu.ru/community/space",
    "title": "Исследователи космоса",
    "rating": 44326
  },
  {
    "link": "https://pikabu.ru/community/Kazakhstan",
    "title": "Пикабушники Казахстана",
    "rating": 43073
  },
  {
    "link": "https://pikabu.ru/community/football",
    "title": "Футбол на Пикабу",
    "rating": 42272
  },
  {
    "link": "https://pikabu.ru/community/SSMP",
    "title": "Лига скорой помощи",
    "rating": 42005
  },
  {
    "link": "https://pikabu.ru/community/LeagueOfArtists",
    "title": "Лига Художников",
    "rating": 41574
  },
  {
    "link": "https://pikabu.ru/community/svoydom",
    "title": "Строительство и ремонт",
    "rating": 40841
  },
  {
    "link": "https://pikabu.ru/community/bigcollection",
    "title": "BigCollection: Всё о кино!",
    "rating": 40650
  },
  {
    "link": "https://pikabu.ru/community/story",
    "title": "Авторские истории",
    "rating": 38899
  },
  {
    "link": "https://pikabu.ru/community/fox",
    "title": "Лисы",
    "rating": 37346
  },
  {
    "link": "https://pikabu.ru/community/roadincident",
    "title": "RoadIncident - ДТП, аварии",
    "rating": 36496
  },
  {
    "link": "https://pikabu.ru/community/Art",
    "title": "Арт",
    "rating": 36130
  },
  {
    "link": "https://pikabu.ru/community/TheWorldofTheWitcher",
    "title": "Мир Ведьмака",
    "rating": 35973
  },
  {
    "link": "https://pikabu.ru/community/science",
    "title": "Наука | Science",
    "rating": 34562
  },
  {
    "link": "https://pikabu.ru/community/Bio",
    "title": "Лига биологов",
    "rating": 30283
  },
  {
    "link": "https://pikabu.ru/community/trash_forum",
    "title": "Исследователи Форумов",
    "rating": 29726
  },
  {
    "link": "https://pikabu.ru/community/spb",
    "title": "ВПитере",
    "rating": 29357
  },
  {
    "link": "https://pikabu.ru/community/AviaTech",
    "title": "Авиация и Техника",
    "rating": 28767
  },
  {
    "link": "https://pikabu.ru/community/liga_pedagogov",
    "title": "Лига Педагогов",
    "rating": 28273
  },
  {
    "link": "https://pikabu.ru/community/taxi",
    "title": "Сообщество таксистов",
    "rating": 27769
  },
  {
    "link": "https://pikabu.ru/community/blizzard",
    "title": "Blizzard на Пикабу",
    "rating": 26477
  },
  {
    "link": "https://pikabu.ru/community/chistomen",
    "title": "Лига Чистомэна",
    "rating": 26353
  },
  {
    "link": "https://pikabu.ru/community/gunsandguns",
    "title": "Оружейная лига",
    "rating": 25966
  },
  {
    "link": "https://pikabu.ru/community/antimoshennic",
    "title": "Антимошенник",
    "rating": 25726
  },
  {
    "link": "https://pikabu.ru/community/localhost",
    "title": "IT-юмор",
    "rating": 24524
  },
  {
    "link": "https://pikabu.ru/community/remont",
    "title": "Сообщество Ремонтёров",
    "rating": 23948
  },
  {
    "link": "https://pikabu.ru/community/child",
    "title": "Дети и родители",
    "rating": 23259
  },
  {
    "link": "https://pikabu.ru/community/lego",
    "title": "LEGO",
    "rating": 23210
  },
  {
    "link": "https://pikabu.ru/community/interesting",
    "title": "Интересные факты",
    "rating": 23159
  },
  {
    "link": "https://pikabu.ru/community/trvlunion",
    "title": "Лига путешественников",
    "rating": 22838
  },
  {
    "link": "https://pikabu.ru/community/Saratovvsomsk",
    "title": "Саратов VS Омск",
    "rating": 21834
  },
  {
    "link": "https://pikabu.ru/community/history",
    "title": "Лига историков",
    "rating": 20372
  },
  {
    "link": "https://pikabu.ru/community/books",
    "title": "Книжная лига",
    "rating": 20240
  },
  {
    "link": "https://pikabu.ru/community/ActiveCitizens",
    "title": "Лига активных граждан",
    "rating": 19578
  },
  {
    "link": "https://pikabu.ru/community/Guns_n_sDef",
    "title": "Оружие и самооборона",
    "rating": 18642
  },
  {
    "link": "https://pikabu.ru/community/sberbank",
    "title": "Сбербанк",
    "rating": 18605
  },
  {
    "link": "https://pikabu.ru/community/warhammer40k",
    "title": "Warhammer 40k",
    "rating": 18376
  },
  {
    "link": "https://pikabu.ru/community/tdu",
    "title": "Лига Дальнобойщиков",
    "rating": 17168
  },
  {
    "link": "https://pikabu.ru/community/medic",
    "title": "Все о медицине",
    "rating": 17133
  },
  {
    "link": "https://pikabu.ru/community/russia",
    "title": "Россия | Фотогалерея",
    "rating": 16390
  },
  {
    "link": "https://pikabu.ru/community/russian_post",
    "title": "Почта России",
    "rating": 16278
  },
  {
    "link": "https://pikabu.ru/community/League_detectives",
    "title": "Лига детективов",
    "rating": 15477
  },
  {
    "link": "https://pikabu.ru/community/kitchen",
    "title": "Кулинарная мастерская",
    "rating": 15442
  },
  {
    "link": "https://pikabu.ru/community/Pikabu_NorthAmerica",
    "title": "Пикабушники Северной Америки",
    "rating": 14792
  },
  {
    "link": "https://pikabu.ru/community/rybalka",
    "title": "Сообщество рыболовов",
    "rating": 14560
  },
  {
    "link": "https://pikabu.ru/community/cosplay",
    "title": "Косплей",
    "rating": 13854
  },
  {
    "link": "https://pikabu.ru/community/LLT",
    "title": "Лига Любителей Татуировки",
    "rating": 13699
  },
  {
    "link": "https://pikabu.ru/community/mlp",
    "title": "My Little Pony",
    "rating": 13208
  },
  {
    "link": "https://pikabu.ru/community/china",
    "title": "Товары из Поднебесной",
    "rating": 13025
  },
  {
    "link": "https://pikabu.ru/community/gribniki",
    "title": "Грибники Пикабу",
    "rating": 12205
  },
  {
    "link": "https://pikabu.ru/community/students",
    "title": "Студенческое общество",
    "rating": 12010
  },
  {
    "link": "https://pikabu.ru/community/psychology",
    "title": "Психология | Psychology",
    "rating": 11889
  },
  {
    "link": "https://pikabu.ru/community/ibc",
    "title": "Информационная безопасность",
    "rating": 11683
  },
  {
    "link": "https://pikabu.ru/community/anime",
    "title": "Аниме",
    "rating": 11443
  },
  {
    "link": "https://pikabu.ru/community/office",
    "title": "Офисные будни",
    "rating": 11100
  },
  {
    "link": "https://pikabu.ru/community/AquaLeague",
    "title": "Аква Лига | Aqua League",
    "rating": 10975
  },
  {
    "link": "https://pikabu.ru/community/alcobushnik",
    "title": "Лига Алкобушников",
    "rating": 10698
  },
  {
    "link": "https://pikabu.ru/community/freelance",
    "title": "Лига фрилансеров",
    "rating": 10483
  },
  {
    "link": "https://pikabu.ru/community/starwars",
    "title": "Star Wars",
    "rating": 10356
  },
  {
    "link": "https://pikabu.ru/community/sovet",
    "title": "Советую посмотреть",
    "rating": 10276
  },
  {
    "link": "https://pikabu.ru/community/90_e",
    "title": "Наши 90-е",
    "rating": 10198
  },
  {
    "link": "https://pikabu.ru/community/electrician",
    "title": "Лига электриков",
    "rating": 10182
  },
  {
    "link": "https://pikabu.ru/community/the_elder_scrolls",
    "title": "The Elder Scrolls",
    "rating": 10078
  },
  {
    "link": "https://pikabu.ru/community/1C8",
    "title": "Программисты 1C:Предприятие 8",
    "rating": 10011
  },
  {
    "link": "https://pikabu.ru/community/Fallout",
    "title": "Fallout",
    "rating": 9982
  },
  {
    "link": "https://pikabu.ru/community/psychotherapy",
    "title": "Лига психотерапии",
    "rating": 9966
  },
  {
    "link": "https://pikabu.ru/community/PerpessaeMiddleAge",
    "title": "Страдающее средневековье",
    "rating": 9951
  },
  {
    "link": "https://pikabu.ru/community/steam",
    "title": "Халява Steam",
    "rating": 9676
  },
  {
    "link": "https://pikabu.ru/community/FotoMir",
    "title": "Фото Мир",
    "rating": 9624
  },
  {
    "link": "https://pikabu.ru/community/TheSimpons",
    "title": "The Simpson's (Симпсоны)",
    "rating": 9357
  },
  {
    "link": "https://pikabu.ru/community/StephenEdwinKing",
    "title": "Стивен Эдвин Кинг",
    "rating": 9128
  },
  {
    "link": "https://pikabu.ru/community/CreepyStory",
    "title": "CreepyStory",
    "rating": 9028
  },
  {
    "link": "https://pikabu.ru/community/bike",
    "title": "Лига Велосипедистов",
    "rating": 8706
  },
  {
    "link": "https://pikabu.ru/community/pikabushniki_vezde",
    "title": "Жизнь пикабушников за границей",
    "rating": 8503
  },
  {
    "link": "https://pikabu.ru/community/Gamedev",
    "title": "Лига Разработчиков Видеоигр",
    "rating": 7978
  },
  {
    "link": "https://pikabu.ru/community/heroes3",
    "title": "Герои Меча и Магии 3",
    "rating": 7554
  },
  {
    "link": "https://pikabu.ru/community/design",
    "title": "Графический и Веб-дизайн",
    "rating": 7407
  },
  {
    "link": "https://pikabu.ru/community/Craft",
    "title": "Крафт",
    "rating": 7302
  },
  {
    "link": "https://pikabu.ru/community/business",
    "title": "Бизнес",
    "rating": 7284
  },
  {
    "link": "https://pikabu.ru/community/furry",
    "title": "Фурри",
    "rating": 7252
  },
  {
    "link": "https://pikabu.ru/community/everlastingsummer",
    "title": "Лагерь Совёнок",
    "rating": 7235
  },
  {
    "link": "https://pikabu.ru/community/VMoscow",
    "title": "ВМоскве",
    "rating": 6979
  },
  {
    "link": "https://pikabu.ru/community/stalker",
    "title": "S.T.A.L.K.E.R.",
    "rating": 6718
  },
  {
    "link": "https://pikabu.ru/community/chemistry",
    "title": "Лига Химиков",
    "rating": 6680
  },
  {
    "link": "https://pikabu.ru/community/ferret",
    "title": "Хорьки",
    "rating": 6604
  },
  {
    "link": "https://pikabu.ru/community/raccoon",
    "title": "Еноты",
    "rating": 6259
  },
  {
    "link": "https://pikabu.ru/community/blablacar",
    "title": "Лига BlaBlaCar",
    "rating": 6198
  },
  {
    "link": "https://pikabu.ru/community/japan",
    "title": "Япония",
    "rating": 6151
  },
  {
    "link": "https://pikabu.ru/community/migraine",
    "title": "Мигрень",
    "rating": 6131
  },
  {
    "link": "https://pikabu.ru/community/marketingover",
    "title": "Маркетинговер",
    "rating": 6104
  },
  {
    "link": "https://pikabu.ru/community/sport",
    "title": "Физкультура и Спорт",
    "rating": 5938
  },
  {
    "link": "https://pikabu.ru/community/goszakupki",
    "title": "Лига Госзакупок",
    "rating": 5918
  },
  {
    "link": "https://pikabu.ru/community/PikabuChina",
    "title": "Китай",
    "rating": 5724
  },
  {
    "link": "https://pikabu.ru/community/potter",
    "title": "Лига Поттероманов",
    "rating": 5660
  },
  {
    "link": "https://pikabu.ru/community/Kriminal",
    "title": "Криминал",
    "rating": 5353
  },
  {
    "link": "https://pikabu.ru/community/bodybuilding",
    "title": "Сообщество Бодибилдинга",
    "rating": 4854
  },
  {
    "link": "https://pikabu.ru/community/south_russia",
    "title": "Южные края России",
    "rating": 4850
  },
  {
    "link": "https://pikabu.ru/community/Psychiatry",
    "title": "Психиатрия",
    "rating": 4833
  },
  {
    "link": "https://pikabu.ru/community/Swimming",
    "title": "Плавание для всех",
    "rating": 4745
  },
  {
    "link": "https://pikabu.ru/community/poezda",
    "title": "Железная дорога",
    "rating": 4731
  },
  {
    "link": "https://pikabu.ru/community/Bollywood",
    "title": "Болливуд",
    "rating": 4670
  },
  {
    "link": "https://pikabu.ru/community/cooks_at_work",
    "title": "Лига Поваров",
    "rating": 4527
  },
  {
    "link": "https://pikabu.ru/community/birds",
    "title": "Лига орнитологии",
    "rating": 4498
  },
  {
    "link": "https://pikabu.ru/community/Far_East",
    "title": "Дальний восток",
    "rating": 4497
  },
  {
    "link": "https://pikabu.ru/community/standmodel",
    "title": "Стендовый моделизм",
    "rating": 4232
  },
  {
    "link": "https://pikabu.ru/community/UrbEx",
    "title": "Заброшенка",
    "rating": 4210
  },
  {
    "link": "https://pikabu.ru/community/pobeda",
    "title": "Чтобы помнили",
    "rating": 4195
  },
  {
    "link": "https://pikabu.ru/community/monogatari",
    "title": "Monogatari Series",
    "rating": 3916
  },
  {
    "link": "https://pikabu.ru/community/basketball",
    "title": "Баскетбол",
    "rating": 3895
  },
  {
    "link": "https://pikabu.ru/community/pirozhki",
    "title": "Пирожки-порошки",
    "rating": 3749
  },
  {
    "link": "https://pikabu.ru/community/classiccars",
    "title": "Classic Cars",
    "rating": 3627
  },
  {
    "link": "https://pikabu.ru/community/dark_half",
    "title": "Истории об отношениях",
    "rating": 3598
  },
  {
    "link": "https://pikabu.ru/community/atv",
    "title": "Дороги не нужны",
    "rating": 3507
  },
  {
    "link": "https://pikabu.ru/community/Egyptology",
    "title": "Лига египтологов",
    "rating": 3500
  },
  {
    "link": "https://pikabu.ru/community/derevo",
    "title": "Работа с деревом",
    "rating": 3457
  },
  {
    "link": "https://pikabu.ru/community/sysodmins_league",
    "title": "Лига Сисадминов",
    "rating": 3433
  },
  {
    "link": "https://pikabu.ru/community/exotarium",
    "title": "Частный экзотариум",
    "rating": 3419
  },
  {
    "link": "https://pikabu.ru/community/street_art",
    "title": "Street Art",
    "rating": 3396
  },
  {
    "link": "https://pikabu.ru/community/BestOfMMA",
    "title": "Боевые единоборства",
    "rating": 3347
  },
  {
    "link": "https://pikabu.ru/community/poety",
    "title": "Сообщество поэтов",
    "rating": 3332
  },
  {
    "link": "https://pikabu.ru/community/liga_znakomstv",
    "title": "Лига Знакомств",
    "rating": 3319
  },
  {
    "link": "https://pikabu.ru/community/rock",
    "title": "Лига рок-музыки",
    "rating": 3106
  },
  {
    "link": "https://pikabu.ru/community/Dreamcatcher",
    "title": "Ловцы снов",
    "rating": 3012
  },
  {
    "link": "https://pikabu.ru/community/sekret_santa",
    "title": "Обмен подарками",
    "rating": 3007
  },
  {
    "link": "https://pikabu.ru/community/belarus",
    "title": "Беларусь",
    "rating": 2946
  },
  {
    "link": "https://pikabu.ru/community/kancolle",
    "title": "Kantai Collection",
    "rating": 2934
  },
  {
    "link": "https://pikabu.ru/community/feature_request",
    "title": "Предложения по Пикабу",
    "rating": 2755
  },
  {
    "link": "https://pikabu.ru/community/moto",
    "title": "Мото",
    "rating": 2750
  },
  {
    "link": "https://pikabu.ru/community/touhou_project",
    "title": "Touhou Project",
    "rating": 2723
  },
  {
    "link": "https://pikabu.ru/community/firefly",
    "title": "Светлячок | Firefly",
    "rating": 2656
  },
  {
    "link": "https://pikabu.ru/community/bdsmstrawberry",
    "title": "Уголок извращений 18+",
    "rating": 2629
  },
  {
    "link": "https://pikabu.ru/community/TECHNO_BROTHER",
    "title": "TECHNO BROTHER",
    "rating": 2555
  },
  {
    "link": "https://pikabu.ru/community/trololooflegue",
    "title": "Лига троллей",
    "rating": 2345
  },
  {
    "link": "https://pikabu.ru/community/knitting_community",
    "title": "Уголок для вязания",
    "rating": 2310
  },
  {
    "link": "https://pikabu.ru/community/ecig",
    "title": "Электронные сигареты",
    "rating": 2298
  },
  {
    "link": "https://pikabu.ru/community/minerals",
    "title": "Лига минералогии",
    "rating": 2265
  },
  {
    "link": "https://pikabu.ru/community/germany",
    "title": "Наши в Германии",
    "rating": 2223
  },
  {
    "link": "https://pikabu.ru/community/hockey",
    "title": "Хоккей",
    "rating": 2174
  },
  {
    "link": "https://pikabu.ru/community/voiceover",
    "title": "Озвучка",
    "rating": 2068
  },
  {
    "link": "https://pikabu.ru/community/lhack",
    "title": "Лайфхак",
    "rating": 2055
  },
  {
    "link": "https://pikabu.ru/community/rescuers",
    "title": "Лига спасателей",
    "rating": 2049
  },
  {
    "link": "https://pikabu.ru/community/Chess",
    "title": "Шахматы",
    "rating": 1999
  },
  {
    "link": "https://pikabu.ru/community/fantakabu",
    "title": "Сообщество фантастов",
    "rating": 1973
  },
  {
    "link": "https://pikabu.ru/community/Polska",
    "title": "Пикабушники в Польше",
    "rating": 1938
  },
  {
    "link": "https://pikabu.ru/community/simphonymusic",
    "title": "Лига Оркестровой Музыки",
    "rating": 1924
  },
  {
    "link": "https://pikabu.ru/community/dark_souls",
    "title": "Dark Souls",
    "rating": 1880
  },
  {
    "link": "https://pikabu.ru/community/metal",
    "title": "Лига метал-музыки",
    "rating": 1870
  },
  {
    "link": "https://pikabu.ru/community/arduino",
    "title": "Arduino & Pi",
    "rating": 1863
  },
  {
    "link": "https://pikabu.ru/community/horses",
    "title": "Конный клуб",
    "rating": 1853
  },
  {
    "link": "https://pikabu.ru/community/bygone_era_in_IT",
    "title": "IT минувших дней",
    "rating": 1826
  },
  {
    "link": "https://pikabu.ru/community/Ligaleni",
    "title": "Лига лени",
    "rating": 1794
  },
  {
    "link": "https://pikabu.ru/community/localwar",
    "title": "Ветеранам локальных войн",
    "rating": 1761
  },
  {
    "link": "https://pikabu.ru/community/lostandfound",
    "title": "Бюро находок",
    "rating": 1748
  },
  {
    "link": "https://pikabu.ru/community/gameshows",
    "title": "Лига Знатоков",
    "rating": 1741
  },
  {
    "link": "https://pikabu.ru/community/new_technologies",
    "title": "Лига Новых Технологий",
    "rating": 1733
  },
  {
    "link": "https://pikabu.ru/community/corvidae",
    "title": "Врановые птицы",
    "rating": 1688
  },
  {
    "link": "https://pikabu.ru/community/bestolkovie_voprosi",
    "title": "Бестолковые вопросы",
    "rating": 1668
  },
  {
    "link": "https://pikabu.ru/community/cities",
    "title": "Лига городов",
    "rating": 1604
  },
  {
    "link": "https://pikabu.ru/community/mlp_creativity",
    "title": "Перья и кисти: MLP творчество",
    "rating": 1584
  },
  {
    "link": "https://pikabu.ru/community/leathercraft",
    "title": "Кожевенное ремесло",
    "rating": 1570
  },
  {
    "link": "https://pikabu.ru/community/mir_milenkih",
    "title": "Мир маленьких животных",
    "rating": 1534
  },
  {
    "link": "https://pikabu.ru/community/zootopia",
    "title": "Зверополис",
    "rating": 1519
  },
  {
    "link": "https://pikabu.ru/community/otters",
    "title": "Выдры",
    "rating": 1476
  },
  {
    "link": "https://pikabu.ru/community/baraholka",
    "title": "Отдам Даром Барахолка",
    "rating": 1464
  },
  {
    "link": "https://pikabu.ru/community/GreenTeaNeko",
    "title": "GreenTeaNeko",
    "rating": 1460
  },
  {
    "link": "https://pikabu.ru/community/undertale",
    "title": "Undertale",
    "rating": 1430
  },
  {
    "link": "https://pikabu.ru/community/leagueoflegends",
    "title": "League of Legends/Лига Легенд",
    "rating": 1427
  },
  {
    "link": "https://pikabu.ru/community/minimalism",
    "title": "Минимализм | Minimalism",
    "rating": 1424
  },
  {
    "link": "https://pikabu.ru/community/art_academy",
    "title": "Младшая Академия Художников",
    "rating": 1337
  },
  {
    "link": "https://pikabu.ru/community/prosecutor",
    "title": "Око государево",
    "rating": 1321
  },
  {
    "link": "https://pikabu.ru/community/plnt_liga",
    "title": "Лига Палеонтологов",
    "rating": 1314
  },
  {
    "link": "https://pikabu.ru/community/show_budgerigar",
    "title": "Волнистые попугаи и \"Чехи\"",
    "rating": 1306
  },
  {
    "link": "https://pikabu.ru/community/RWBY",
    "title": "RWBY",
    "rating": 1298
  },
  {
    "link": "https://pikabu.ru/community/unidc",
    "title": "Вселенная DC",
    "rating": 1240
  },
  {
    "link": "https://pikabu.ru/community/steins_gate",
    "title": "Лаборатория Гаджетов Будущего",
    "rating": 1227
  },
  {
    "link": "https://pikabu.ru/community/serials",
    "title": "Сериаломания",
    "rating": 1208
  },
  {
    "link": "https://pikabu.ru/community/aibolit",
    "title": "Айболит. Помощь животным",
    "rating": 1158
  },
  {
    "link": "https://pikabu.ru/community/ingress",
    "title": "Nia lab. INGRESS community",
    "rating": 1134
  },
  {
    "link": "https://pikabu.ru/community/Bank",
    "title": "Банковское сообщество",
    "rating": 1132
  },
  {
    "link": "https://pikabu.ru/community/create",
    "title": "Создайте сообщество",
    "rating": 1113
  },
  {
    "link": "https://pikabu.ru/community/web",
    "title": "Web-технологии",
    "rating": 1108
  },
  {
    "link": "https://pikabu.ru/community/CNC",
    "title": "Лига ЧПУшников",
    "rating": 1077
  },
  {
    "link": "https://pikabu.ru/community/WHO",
    "title": "Лига ТАРДИС",
    "rating": 961
  },
  {
    "link": "https://pikabu.ru/community/Coffee",
    "title": "Кофе мой друг",
    "rating": 932
  },
  {
    "link": "https://pikabu.ru/community/pixelart",
    "title": "Pixel art",
    "rating": 926
  },
  {
    "link": "https://pikabu.ru/community/italia_pikabu",
    "title": "Пикабушники Италии",
    "rating": 917
  },
  {
    "link": "https://pikabu.ru/community/liga_dobra",
    "title": "Лига Добра",
    "rating": 897
  },
  {
    "link": "https://pikabu.ru/community/scpfoundation",
    "title": "SCP Foundation",
    "rating": 885
  },
  {
    "link": "https://pikabu.ru/community/geo_liga",
    "title": "Лига Геологов",
    "rating": 875
  },
  {
    "link": "https://pikabu.ru/community/papercraft",
    "title": "Papercraft - шедевры из бумаги",
    "rating": 863
  },
  {
    "link": "https://pikabu.ru/community/linux",
    "title": "GNU/Linux",
    "rating": 834
  },
  {
    "link": "https://pikabu.ru/community/musicleague",
    "title": "Лига музыкантов",
    "rating": 802
  },
  {
    "link": "https://pikabu.ru/community/Crimea",
    "title": "Республика Крым",
    "rating": 782
  },
  {
    "link": "https://pikabu.ru/community/RetroWavers",
    "title": "RetroWavers",
    "rating": 757
  },
  {
    "link": "https://pikabu.ru/community/education",
    "title": "Лига образования",
    "rating": 744
  },
  {
    "link": "https://pikabu.ru/community/data",
    "title": "Статистика",
    "rating": 741
  },
  {
    "link": "https://pikabu.ru/community/parachute",
    "title": "Лига парашютистов",
    "rating": 739
  },
  {
    "link": "https://pikabu.ru/community/cookie",
    "title": "Маскоты Пикабу",
    "rating": 735
  },
  {
    "link": "https://pikabu.ru/community/historyoflifeandart",
    "title": "История быта и искусств",
    "rating": 721
  },
  {
    "link": "https://pikabu.ru/community/Tolkien",
    "title": "Средиземье - мир Толкина",
    "rating": 717
  },
  {
    "link": "https://pikabu.ru/community/Comix_Zone",
    "title": "Comix Zone",
    "rating": 659
  },
  {
    "link": "https://pikabu.ru/community/boardgames",
    "title": "Настольные игры",
    "rating": 641
  },
  {
    "link": "https://pikabu.ru/community/masseffect",
    "title": "Mass Effect",
    "rating": 635
  },
  {
    "link": "https://pikabu.ru/community/dragons",
    "title": "Драконы",
    "rating": 634
  },
  {
    "link": "https://pikabu.ru/community/lso",
    "title": "Лига сферы обслуживания",
    "rating": 607
  },
  {
    "link": "https://pikabu.ru/community/diet_power",
    "title": "Лига диетологов",
    "rating": 602
  },
  {
    "link": "https://pikabu.ru/community/psbattles",
    "title": "Лига фотожоперов",
    "rating": 598
  },
  {
    "link": "https://pikabu.ru/community/narkon",
    "title": "Народный контроль",
    "rating": 593
  },
  {
    "link": "https://pikabu.ru/community/cgimedia",
    "title": "CGI Media",
    "rating": 587
  },
  {
    "link": "https://pikabu.ru/community/agriculture",
    "title": "Лига Сельского хозяйства",
    "rating": 573
  },
  {
    "link": "https://pikabu.ru/community/el_tr",
    "title": "Электротранспорт",
    "rating": 549
  },
  {
    "link": "https://pikabu.ru/community/its_a_trap",
    "title": "Милота с подвохом",
    "rating": 526
  },
  {
    "link": "https://pikabu.ru/community/katawashoujo",
    "title": "Katawa Shoujo",
    "rating": 515
  },
  {
    "link": "https://pikabu.ru/community/Kyrgyzstan",
    "title": "Пикабушники Кыргызстана",
    "rating": 490
  },
  {
    "link": "https://pikabu.ru/community/Zelenka",
    "title": "Зелёнка (ландшафтный дизайн)",
    "rating": 467
  },
  {
    "link": "https://pikabu.ru/community/quadrocopter",
    "title": "Квадрокоптеры, фото и видео",
    "rating": 457
  },
  {
    "link": "https://pikabu.ru/community/cars_from_ussr",
    "title": "Автомобили из СССР",
    "rating": 454
  },
  {
    "link": "https://pikabu.ru/community/bahja",
    "title": "Баня",
    "rating": 450
  },
  {
    "link": "https://pikabu.ru/community/watersexmagic",
    "title": "Прыжки в воду. Водные забавы.",
    "rating": 433
  },
  {
    "link": "https://pikabu.ru/community/aviation",
    "title": "Авиация",
    "rating": 419
  },
  {
    "link": "https://pikabu.ru/community/hunting",
    "title": "Клуб охотников",
    "rating": 414
  },
  {
    "link": "https://pikabu.ru/community/calligraphy",
    "title": "Лига каллиграфов",
    "rating": 412
  },
  {
    "link": "https://pikabu.ru/community/microsoft_news",
    "title": "Microsoft News",
    "rating": 410
  },
  {
    "link": "https://pikabu.ru/community/Nasuverse",
    "title": "Nasuverse",
    "rating": 404
  },
  {
    "link": "https://pikabu.ru/community/cartoons",
    "title": "Cartoon & Animation",
    "rating": 396
  },
  {
    "link": "https://pikabu.ru/community/origami",
    "title": "Лига Оригами",
    "rating": 390
  },
  {
    "link": "https://pikabu.ru/community/rugby",
    "title": "Регби",
    "rating": 390
  },
  {
    "link": "https://pikabu.ru/community/guitar",
    "title": "Лига гитаристов",
    "rating": 377
  },
  {
    "link": "https://pikabu.ru/community/demciv",
    "title": "Демократия в Civilization 5",
    "rating": 367
  },
  {
    "link": "https://pikabu.ru/community/stellaris",
    "title": "Stellaris 4X-стратегия",
    "rating": 349
  },
  {
    "link": "https://pikabu.ru/community/liga_gramotnosti",
    "title": "Лига грамотности",
    "rating": 341
  },
  {
    "link": "https://pikabu.ru/community/Inkopolis",
    "title": "Инкополис",
    "rating": 335
  },
  {
    "link": "https://pikabu.ru/community/muscle_girls",
    "title": "Крепкие Девушки",
    "rating": 317
  },
  {
    "link": "https://pikabu.ru/community/rabbit",
    "title": "Декоративные кролики и зайцы",
    "rating": 315
  },
  {
    "link": "https://pikabu.ru/community/retrogaming",
    "title": "Уголок ретрогеймера",
    "rating": 314
  },
  {
    "link": "https://pikabu.ru/community/ligaenglish",
    "title": "EnglishPub",
    "rating": 311
  },
  {
    "link": "https://pikabu.ru/community/Foto_from_Phone",
    "title": "Фото с мобильного",
    "rating": 293
  },
  {
    "link": "https://pikabu.ru/community/warhammerfb",
    "title": "Warhammer Fantasy",
    "rating": 292
  },
  {
    "link": "https://pikabu.ru/community/audio",
    "title": "Аудио и видео",
    "rating": 292
  },
  {
    "link": "https://pikabu.ru/community/newTV",
    "title": "Новогодний эфир",
    "rating": 287
  },
  {
    "link": "https://pikabu.ru/community/numismatics",
    "title": "Сообщество нумизматов",
    "rating": 287
  },
  {
    "link": "https://pikabu.ru/community/World_of_building",
    "title": "World of building | Сооружения",
    "rating": 285
  },
  {
    "link": "https://pikabu.ru/community/birdwatching",
    "title": "Бёрдвотчинг",
    "rating": 279
  },
  {
    "link": "https://pikabu.ru/community/treasurehunters",
    "title": "Сообщество Кладоискателей",
    "rating": 277
  },
  {
    "link": "https://pikabu.ru/community/warcraft",
    "title": "Warcraft",
    "rating": 252
  },
  {
    "link": "https://pikabu.ru/community/tortoff",
    "title": "Лига тортов",
    "rating": 230
  },
  {
    "link": "https://pikabu.ru/community/infografika",
    "title": "Инфографика",
    "rating": 229
  },
  {
    "link": "https://pikabu.ru/community/DarkestDungeon",
    "title": "Darkest Dungeon",
    "rating": 217
  },
  {
    "link": "https://pikabu.ru/community/hawkwings",
    "title": "Лига любителей хищных птиц",
    "rating": 214
  },
  {
    "link": "https://pikabu.ru/community/elmix",
    "title": "Электромеханик+",
    "rating": 213
  },
  {
    "link": "https://pikabu.ru/community/Overwatch",
    "title": "Overwatch",
    "rating": 211
  },
  {
    "link": "https://pikabu.ru/community/liga_3D",
    "title": "Лига 3D принтеров",
    "rating": 202
  },
  {
    "link": "https://pikabu.ru/community/Liga_pchelovodstva",
    "title": "Лига пчеловодства",
    "rating": 202
  },
  {
    "link": "https://pikabu.ru/community/sculpture",
    "title": "Скульптура",
    "rating": 197
  },
  {
    "link": "https://pikabu.ru/community/Lovecraft",
    "title": "Лавкрафт",
    "rating": 187
  },
  {
    "link": "https://pikabu.ru/community/beliveinsteven",
    "title": "Вселенная Стивена",
    "rating": 187
  },
  {
    "link": "https://pikabu.ru/community/santech",
    "title": "Сантехники-слесаря",
    "rating": 183
  },
  {
    "link": "https://pikabu.ru/community/call_center",
    "title": "Работники колл-центра",
    "rating": 181
  },
  {
    "link": "https://pikabu.ru/community/historyandlegends",
    "title": "Истории и легенды",
    "rating": 169
  },
  {
    "link": "https://pikabu.ru/community/seamen",
    "title": "Сообщество моряков",
    "rating": 168
  },
  {
    "link": "https://pikabu.ru/community/prizyv",
    "title": "Призыв в армию.",
    "rating": 163
  },
  {
    "link": "https://pikabu.ru/community/grow",
    "title": "Прогрессивное растениеводство",
    "rating": 146
  },
  {
    "link": "https://pikabu.ru/community/theatre",
    "title": "Сообщество театралов",
    "rating": 140
  },
  {
    "link": "https://pikabu.ru/community/lost_games",
    "title": "Лига Потерянных Игр",
    "rating": 138
  },
  {
    "link": "https://pikabu.ru/community/family",
    "title": "Моя Семья",
    "rating": 121
  },
  {
    "link": "https://pikabu.ru/community/Wot",
    "title": "World of Tanks",
    "rating": 113
  },
  {
    "link": "https://pikabu.ru/community/creativecraft",
    "title": "Диорамы",
    "rating": 111
  },
  {
    "link": "https://pikabu.ru/community/countryballs",
    "title": "Countryballs",
    "rating": 102
  },
  {
    "link": "https://pikabu.ru/community/bugreports",
    "title": "Багрепорты",
    "rating": 98
  },
  {
    "link": "https://pikabu.ru/community/MtG",
    "title": "Magic: The Gathering",
    "rating": 94
  },
  {
    "link": "https://pikabu.ru/community/showerwisdom",
    "title": "Мысли в дУше",
    "rating": 84
  },
  {
    "link": "https://pikabu.ru/community/knife",
    "title": "Ножи",
    "rating": 83
  },
  {
    "link": "https://pikabu.ru/community/formula_1",
    "title": "Формула 1",
    "rating": 83
  },
  {
    "link": "https://pikabu.ru/community/StormChasers",
    "title": "Лига охотников за грозами",
    "rating": 81
  },
  {
    "link": "https://pikabu.ru/community/KlubStrategov",
    "title": "Клуб Стратегов",
    "rating": 78
  },
  {
    "link": "https://pikabu.ru/community/collect",
    "title": "Лига коллекционеров",
    "rating": 77
  },
  {
    "link": "https://pikabu.ru/community/stomatology",
    "title": "Стоматология",
    "rating": 76
  },
  {
    "link": "https://pikabu.ru/community/playgirl",
    "title": "Playgirl. Первый женский",
    "rating": 75
  },
  {
    "link": "https://pikabu.ru/community/pubg",
    "title": "Playerunknown's Battlegrounds",
    "rating": 72
  },
  {
    "link": "https://pikabu.ru/community/umor_shmumor",
    "title": "Специфический юмор",
    "rating": 71
  },
  {
    "link": "https://pikabu.ru/community/discounthunters",
    "title": "Охотники за скидками",
    "rating": 71
  },
  {
    "link": "https://pikabu.ru/community/Supernatural",
    "title": "Сверхъестественное",
    "rating": 68
  },
  {
    "link": "https://pikabu.ru/community/yandex_info",
    "title": "Лига Яндекса Пикабу [ЛЯП]",
    "rating": 66
  },
  {
    "link": "https://pikabu.ru/community/translation",
    "title": "Перевод и переводчики",
    "rating": 56
  },
  {
    "link": "https://pikabu.ru/community/zapchasti",
    "title": "Лига автоснабженцев Пикабу",
    "rating": 55
  },
  {
    "link": "https://pikabu.ru/community/macro",
    "title": "Лига любителей макрофото",
    "rating": 54
  },
  {
    "link": "https://pikabu.ru/community/DragonAge",
    "title": "The World of Dragon Age",
    "rating": 52
  },
  {
    "link": "https://pikabu.ru/community/retro",
    "title": "Ретро",
    "rating": 52
  },
  {
    "link": "https://pikabu.ru/community/cyberpunk",
    "title": "Киберпанк",
    "rating": 48
  },
  {
    "link": "https://pikabu.ru/community/poker",
    "title": "Poker",
    "rating": 46
  },
  {
    "link": "https://pikabu.ru/community/exoticart",
    "title": "Экзотика искусства",
    "rating": 43
  },
  {
    "link": "https://pikabu.ru/community/polymerclay",
    "title": "Полимерная глина",
    "rating": 43
  },
  {
    "link": "https://pikabu.ru/community/airsoft_league",
    "title": "Лига Страйкбола",
    "rating": 37
  },
  {
    "link": "https://pikabu.ru/community/redarmyairsoft",
    "title": "Red Army Airsoft - страйкбол",
    "rating": 37
  },
  {
    "link": "https://pikabu.ru/community/skandinaviaandworld",
    "title": "Скандинавия и Мир",
    "rating": 37
  },
  {
    "link": "https://pikabu.ru/community/animators",
    "title": "Лига Аниматоров",
    "rating": 36
  },
  {
    "link": "https://pikabu.ru/community/antichnost",
    "title": "Античность",
    "rating": 36
  },
  {
    "link": "https://pikabu.ru/community/broken_hearts",
    "title": "Лига разбитых сердец",
    "rating": 35
  },
  {
    "link": "https://pikabu.ru/community/architects",
    "title": "Лига Архитекторов",
    "rating": 35
  },
  {
    "link": "https://pikabu.ru/community/photoshopme",
    "title": "Отфотошопьте, пожалуйста",
    "rating": 34
  },
  {
    "link": "https://pikabu.ru/community/strashnointeresno",
    "title": "Я знаю чего ты боишься",
    "rating": 32
  },
  {
    "link": "https://pikabu.ru/community/AmericanSports",
    "title": "NBA NFL NHL MLB NCAA",
    "rating": 30
  },
  {
    "link": "https://pikabu.ru/community/hearthstone",
    "title": "Hearthstone",
    "rating": 27
  },
  {
    "link": "https://pikabu.ru/community/sovmults",
    "title": "Советские мультфильмы",
    "rating": 27
  },
  {
    "link": "https://pikabu.ru/community/vector_graphics",
    "title": "Векторная графика",
    "rating": 25
  },
  {
    "link": "https://pikabu.ru/community/androsoft",
    "title": "Андроид ремонтеры",
    "rating": 22
  },
  {
    "link": "https://pikabu.ru/community/twitter",
    "title": "Твиттер | Twitter",
    "rating": 22
  },
  {
    "link": "https://pikabu.ru/community/metalgear",
    "title": "Metal Gear",
    "rating": 21
  },
  {
    "link": "https://pikabu.ru/community/poznavatelno",
    "title": "Это познавательно",
    "rating": 21
  },
  {
    "link": "https://pikabu.ru/community/python",
    "title": "Программирование на python",
    "rating": 19
  },
  {
    "link": "https://pikabu.ru/community/Neptunia",
    "title": "Hyperdimension Neptunia",
    "rating": 19
  },
  {
    "link": "https://pikabu.ru/community/QualityAssurance",
    "title": "Quality Assurance",
    "rating": 18
  },
  {
    "link": "https://pikabu.ru/community/cover",
    "title": "Кавер",
    "rating": 17
  },
  {
    "link": "https://pikabu.ru/community/Gromogon",
    "title": "Крысиные Хроники",
    "rating": 17
  },
  {
    "link": "https://pikabu.ru/community/meat",
    "title": "Мясо. Коротко и ясно.",
    "rating": 16
  },
  {
    "link": "https://pikabu.ru/community/science_disputes",
    "title": "Споры о науке",
    "rating": 16
  },
  {
    "link": "https://pikabu.ru/community/histfencing",
    "title": "Историческое фехтование",
    "rating": 16
  },
  {
    "link": "https://pikabu.ru/community/playstation",
    "title": "PlayStation",
    "rating": 15
  },
  {
    "link": "https://pikabu.ru/community/wordmans",
    "title": "Лига Писателей",
    "rating": 15
  },
  {
    "link": "https://pikabu.ru/community/kpop",
    "title": "K-POP",
    "rating": 14
  },
  {
    "link": "https://pikabu.ru/community/audiology",
    "title": "Ваш слух и слуховые аппараты",
    "rating": 13
  },
  {
    "link": "https://pikabu.ru/community/Mercenaries",
    "title": "Наёмники",
    "rating": 13
  },
  {
    "link": "https://pikabu.ru/community/miriskusstva",
    "title": "Лига искусствоведов",
    "rating": 12
  },
  {
    "link": "https://pikabu.ru/community/Elite_Dangerous",
    "title": "Elite: Dangerous",
    "rating": 12
  },
  {
    "link": "https://pikabu.ru/community/biser",
    "title": "Мир бисера",
    "rating": 12
  },
  {
    "link": "https://pikabu.ru/community/rod",
    "title": "Лига генеалогов | родословная",
    "rating": 12
  },
  {
    "link": "https://pikabu.ru/community/liga_dzhiperov",
    "title": "Лига джиперов",
    "rating": 10
  },
  {
    "link": "https://pikabu.ru/community/40000_pododeyalko",
    "title": "Лига 40000-го года",
    "rating": 9
  },
  {
    "link": "https://pikabu.ru/community/unity",
    "title": "Unity",
    "rating": 9
  },
  {
    "link": "https://pikabu.ru/community/X_Files",
    "title": "X-Files",
    "rating": 9
  },
  {
    "link": "https://pikabu.ru/community/bigtennis",
    "title": "Большой теннис",
    "rating": 8
  },
  {
    "link": "https://pikabu.ru/community/one_day",
    "title": "Один день из жизни",
    "rating": 8
  },
  {
    "link": "https://pikabu.ru/community/roller",
    "title": "Лига Роллеров",
    "rating": 8
  },
  {
    "link": "https://pikabu.ru/community/ndv",
    "title": "Лига Недвижимости",
    "rating": 8
  },
  {
    "link": "https://pikabu.ru/community/Baltic",
    "title": "Пикабушники Прибалтики",
    "rating": 8
  },
  {
    "link": "https://pikabu.ru/community/pokemongo",
    "title": "Pokemon GO",
    "rating": 7
  },
  {
    "link": "https://pikabu.ru/community/mathematicians",
    "title": "Лига математиков",
    "rating": 6
  },
  {
    "link": "https://pikabu.ru/community/soft",
    "title": "Полезный софт и расширения",
    "rating": 6
  },
  {
    "link": "https://pikabu.ru/community/polyglot_league",
    "title": "Лига Полиглотов",
    "rating": 5
  },
  {
    "link": "https://pikabu.ru/community/divan_expert",
    "title": "Лига диванных экспертов",
    "rating": 5
  },
  {
    "link": "https://pikabu.ru/community/philosophy",
    "title": "Философия",
    "rating": 5
  },
  {
    "link": "https://pikabu.ru/community/wot_blitz",
    "title": "WoT Blitz",
    "rating": 5
  },
  {
    "link": "https://pikabu.ru/community/podvoh",
    "title": "Лига Подводных охотников",
    "rating": 5
  },
  {
    "link": "https://pikabu.ru/community/lightbox",
    "title": "Lightbox - идеальный подарок",
    "rating": 4
  },
  {
    "link": "https://pikabu.ru/community/dota2",
    "title": "Dota 2",
    "rating": 4
  },
  {
    "link": "https://pikabu.ru/community/Book_of_complaints",
    "title": "Книга жалоб",
    "rating": 4
  },
  {
    "link": "https://pikabu.ru/community/The_Legend_of_Zelda",
    "title": "The Legend of Zelda",
    "rating": 4
  },
  {
    "link": "https://pikabu.ru/community/smile",
    "title": "Лига парейдоликов",
    "rating": 3
  },
  {
    "link": "https://pikabu.ru/community/analytics_news",
    "title": "Новости валютного рынка",
    "rating": 3
  },
  {
    "link": "https://pikabu.ru/community/android",
    "title": "Android Developers",
    "rating": 3
  },
  {
    "link": "https://pikabu.ru/community/silenthill",
    "title": "Silent Hill",
    "rating": 3
  },
  {
    "link": "https://pikabu.ru/community/massage",
    "title": "Массаж",
    "rating": 2
  },
  {
    "link": "https://pikabu.ru/community/postapocalypse",
    "title": "Постапокалипсис",
    "rating": 2
  },
  {
    "link": "https://pikabu.ru/community/copydesant",
    "title": "КопиДесант",
    "rating": 2
  },
  {
    "link": "https://pikabu.ru/community/space_engineers",
    "title": "Space Engineers",
    "rating": 1
  },
  {
    "link": "https://pikabu.ru/community/journalists",
    "title": "Лига журналистов",
    "rating": 1
  },
  {
    "link": "https://pikabu.ru/community/link",
    "title": "Лига связистов",
    "rating": 0
  },
  {
    "link": "https://pikabu.ru/community/technology",
    "title": "Лига технологов",
    "rating": 0
  },
  {
    "link": "https://pikabu.ru/community/rukojopliga",
    "title": "Лига рукожопов",
    "rating": 0
  },
  {
    "link": "https://pikabu.ru/community/manprogress",
    "title": "Развитие и самореализация",
    "rating": 0
  },
  {
    "link": "https://pikabu.ru/community/bollywoodnews",
    "title": "BollywoodNews",
    "rating": 0
  },
  {
    "link": "https://pikabu.ru/community/php",
    "title": "Программирование на PHP",
    "rating": -1
  },
  {
    "link": "https://pikabu.ru/community/drift",
    "title": "Drift Community",
    "rating": -1
  },
  {
    "link": "https://pikabu.ru/community/apple",
    "title": "Лига Яблок",
    "rating": -1
  },
  {
    "link": "https://pikabu.ru/community/GameRoom",
    "title": "Игровая комната Пикабу",
    "rating": -1
  },
  {
    "link": "https://pikabu.ru/community/studentengineer",
    "title": "Студент-Инженер",
    "rating": -1
  },
  {
    "link": "https://pikabu.ru/community/ingenerium",
    "title": "Инженериум",
    "rating": -2
  },
  {
    "link": "https://pikabu.ru/community/free",
    "title": "Халява",
    "rating": -2
  },
  {
    "link": "https://pikabu.ru/community/Australia",
    "title": "Австралия",
    "rating": -3
  },
  {
    "link": "https://pikabu.ru/community/IDL",
    "title": "Industrial Design League",
    "rating": -3
  },
  {
    "link": "https://pikabu.ru/community/eSport",
    "title": "eSport: всё о киберспорте",
    "rating": -3
  },
  {
    "link": "https://pikabu.ru/community/svtfoe",
    "title": "Star vs. the Forces of Evil",
    "rating": -3
  },
  {
    "link": "https://pikabu.ru/community/shutup_take_my_money",
    "title": "Заткнись и возьми мои деньги",
    "rating": -3
  },
  {
    "link": "https://pikabu.ru/community/fantasy",
    "title": "Миры Фэнтези",
    "rating": -3
  },
  {
    "link": "https://pikabu.ru/community/spbsport",
    "title": "Спортивный Петербург",
    "rating": -4
  },
  {
    "link": "https://pikabu.ru/community/Liga_zanud",
    "title": "Лига Зануд",
    "rating": -5
  },
  {
    "link": "https://pikabu.ru/community/seosmm",
    "title": "Сообщество SMM и SEO",
    "rating": -5
  },
  {
    "link": "https://pikabu.ru/community/tea_blog",
    "title": "Мир. Покой. Чай",
    "rating": -5
  },
  {
    "link": "https://pikabu.ru/community/gaz_auto",
    "title": "ГАЗ авто",
    "rating": -6
  },
  {
    "link": "https://pikabu.ru/community/nightposts",
    "title": "Ночные посты",
    "rating": -6
  },
  {
    "link": "https://pikabu.ru/community/HelpRemont",
    "title": "Сообщество Ремонтёров - Помощь",
    "rating": -6
  },
  {
    "link": "https://pikabu.ru/community/it_projects",
    "title": "ИТ проекты пикабушников",
    "rating": -7
  },
  {
    "link": "https://pikabu.ru/community/restorannaya_kritika",
    "title": "Лига ресторанных критиков",
    "rating": -7
  },
  {
    "link": "https://pikabu.ru/community/Postcrossing",
    "title": "Обмен письмами",
    "rating": -7
  },
  {
    "link": "https://pikabu.ru/community/freemasonry",
    "title": "Масонство • Freemasonry",
    "rating": -8
  },
  {
    "link": "https://pikabu.ru/community/tiktak",
    "title": "Капсула времени",
    "rating": -8
  },
  {
    "link": "https://pikabu.ru/community/clashroyale",
    "title": "Clash Royale & Clash of Clans",
    "rating": -8
  },
  {
    "link": "https://pikabu.ru/community/Search",
    "title": "Поиск по описанию",
    "rating": -8
  },
  {
    "link": "https://pikabu.ru/community/Rammstein",
    "title": "Rammstein",
    "rating": -9
  },
  {
    "link": "https://pikabu.ru/community/askpikabu",
    "title": "Спроси Пикабу",
    "rating": -9
  },
  {
    "link": "https://pikabu.ru/community/rap",
    "title": "Hip-Hop&Rap",
    "rating": -12
  },
  {
    "link": "https://pikabu.ru/community/csgo",
    "title": "CS:GO",
    "rating": -13
  },
  {
    "link": "https://pikabu.ru/community/standup",
    "title": "Stand-Up | Стендап",
    "rating": -13
  },
  {
    "link": "https://pikabu.ru/community/anti_alko",
    "title": "Борьба с вредными привычками",
    "rating": -14
  },
  {
    "link": "https://pikabu.ru/community/android_news",
    "title": "Android",
    "rating": -18
  },
  {
    "link": "https://pikabu.ru/community/ijustrealised",
    "title": "Я тут осознал что...",
    "rating": -19
  },
  {
    "link": "https://pikabu.ru/community/What_the_movie",
    "title": "Что за фильм?",
    "rating": -20
  },
  {
    "link": "https://pikabu.ru/community/4inovniki",
    "title": "Лига чиновников",
    "rating": -20
  },
  {
    "link": "https://pikabu.ru/community/videoediting",
    "title": "Видеомонтаж",
    "rating": -22
  },
  {
    "link": "https://pikabu.ru/community/Epic_life",
    "title": "Epic life",
    "rating": -26
  },
  {
    "link": "https://pikabu.ru/community/fivenightsatfreddy",
    "title": "five nights at freddy's",
    "rating": -31
  },
  {
    "link": "https://pikabu.ru/community/metro",
    "title": "Люди в Метро",
    "rating": -33
  },
  {
    "link": "https://pikabu.ru/community/esoterics",
    "title": "Эзотерика и магия",
    "rating": -35
  },
  {
    "link": "https://pikabu.ru/community/molodye_biznesmeny",
    "title": "Молодые предприниматели",
    "rating": -36
  },
  {
    "link": "https://pikabu.ru/community/support_community",
    "title": "Дела сообществ",
    "rating": -38
  },
  {
    "link": "https://pikabu.ru/community/pop",
    "title": "Лига поп-музыки",
    "rating": -38
  },
  {
    "link": "https://pikabu.ru/community/tv_fans",
    "title": "Любители ТВ",
    "rating": -45
  },
  {
    "link": "https://pikabu.ru/community/IOS",
    "title": "Всё об iOS",
    "rating": -59
  },
  {
    "link": "https://pikabu.ru/community/army_humor",
    "title": "Армейский юмор",
    "rating": -73
  },
  {
    "link": "https://pikabu.ru/community/karikatura",
    "title": "Карикатуры и шаржи",
    "rating": -83
  },
  {
    "link": "https://pikabu.ru/community/cryptocurrency",
    "title": "Лига Криптовалют",
    "rating": -86
  },
  {
    "link": "https://pikabu.ru/community/moderator",
    "title": "Вопросы по модерации",
    "rating": -217
  }
]
